CHANGES.rst
MANIFEST.in
Makefile
README.rst
pip-requirements.txt
setup.py
test-requirements.txt
tox.ini
circus_web.egg-info/PKG-INFO
circus_web.egg-info/SOURCES.txt
circus_web.egg-info/dependency_links.txt
circus_web.egg-info/entry_points.txt
circus_web.egg-info/not-zip-safe
circus_web.egg-info/requires.txt
circus_web.egg-info/top_level.txt
circusweb/__init__.py
circusweb/circushttpd.py
circusweb/client.py
circusweb/controller.py
circusweb/namespace.py
circusweb/server.py
circusweb/session.py
circusweb/stats_client.py
circusweb/util.py
circusweb/media/circus.css
circusweb/media/circus.js
circusweb/media/circus.png
circusweb/media/d3.v2.js
circusweb/media/favicon.ico
circusweb/media/jquery.min.js
circusweb/media/jquery.sparkline.min.js
circusweb/media/kill.png
circusweb/media/rickshaw.min.css
circusweb/media/rickshaw.min.js
circusweb/media/socket.io.js
circusweb/templates/base.html
circusweb/templates/connect.html
circusweb/templates/index.html
circusweb/templates/sockets.html
circusweb/templates/watcher.html
circusweb/tests/__init__.py
circusweb/tests/test_utils.py
circusweb/tests/test_web.py