Metadata-Version: 1.1
Name: circus-web
Version: 0.5
Summary: Circus Web Dashboard
Home-page: UNKNOWN
Author: Mozilla Foundation & contributors
Author-email: services-dev@lists.mozila.org
License: UNKNOWN
Platform: UNKNOWN
Classifier: Programming Language :: Python
Classifier: Programming Language :: Python :: 2.6
Classifier: Programming Language :: Python :: 2.7
Classifier: License :: OSI Approved :: Apache Software License
Classifier: Development Status :: 3 - Alpha
